scikit_posthocs/__init__.py
scikit_posthocs/_global.py
scikit_posthocs/_omnibus.py
scikit_posthocs/_outliers.py
scikit_posthocs/_plotting.py
scikit_posthocs/_posthocs.py
scikit_posthocs-0.11.3.dist-info/LICENSE
scikit_posthocs-0.11.3.dist-info/METADATA
scikit_posthocs-0.11.3.dist-info/WHEEL
scikit_posthocs-0.11.3.dist-info/top_level.txt
scikit_posthocs-0.11.3.dist-info/RECORD
