Metadata-Version: 2.2
Name: scikit-posthocs
Version: 0.11.3
Summary: Statistical post-hoc analysis and outlier detection algorithms
Author-email: Maksim Terpilovskii <maximtrp@gmail.com>
License: Copyright (c) 2024 Maksim Terpilovskii
Project-URL: homepage, https://github.com/maximtrp/scikit-posthocs
Project-URL: documentation, https://scikit-posthocs.rtfd.io
Keywords: statistics,stats,posthoc,anova,data science
Classifier: Development Status :: 5 - Production/Stable
Classifier: Intended Audience :: Education
Classifier: Intended Audience :: Information Technology
Classifier: Intended Audience :: Science/Research
Classifier: Topic :: Scientific/Engineering :: Information Analysis
Classifier: Topic :: Scientific/Engineering :: Mathematics
Classifier: License :: OSI Approved :: MIT License
Classifier: Programming Language :: Python :: 3
Classifier: Programming Language :: Python :: 3.9
Classifier: Programming Language :: Python :: 3.10
Classifier: Programming Language :: Python :: 3.11
Classifier: Programming Language :: Python :: 3.12
Classifier: Programming Language :: Python :: 3.13
Requires-Python: >=3.9
License-File: LICENSE
Requires-Dist: numpy
Requires-Dist: scipy>=1.9.0
Requires-Dist: statsmodels
Requires-Dist: pandas>=0.20.0
Requires-Dist: seaborn
Requires-Dist: matplotlib
Provides-Extra: test
Requires-Dist: pytest; extra == "test"
Requires-Dist: coverage; extra == "test"
